kitti_aug/__init__.py
kitti_aug/aug_utils.py
kitti_aug/bev_reader.py
kitti_aug/calib_reader.py
kitti_aug/data_reader.py
kitti_aug/fv_utils.py
kitti_aug/image_reader.py
kitti_aug/label_reader.py
kitti_aug/param_object.py
kitti_aug/utils.py
kitti_aug-0.2.dist-info/LICENSE
kitti_aug-0.2.dist-info/METADATA
kitti_aug-0.2.dist-info/WHEEL
kitti_aug-0.2.dist-info/top_level.txt
kitti_aug-0.2.dist-info/RECORD
