Metadata-Version: 2.1
Name: kitti-aug
Version: 0.2
Summary: UNKNOWN
Home-page: https://github.com/MariamMohamedFawzy/KittiAug
Author: Mariam Mohamed
Author-email: maryammohamed61@gmail.com
License: MIT
Platform: UNKNOWN
